Twitch_Edog0049a/Scope.py
Twitch_Edog0049a/SubscriptionTypes.py
Twitch_Edog0049a/__init__.py
Twitch_Edog0049a/API/Exceptions.py
Twitch_Edog0049a/API/TwitchAPI.py
Twitch_Edog0049a/API/_ApiRequest.py
Twitch_Edog0049a/API/__init__.py
Twitch_Edog0049a/API/api flow.svg
Twitch_Edog0049a/API/Resources/Ads.py
Twitch_Edog0049a/API/Resources/Analytics.py
Twitch_Edog0049a/API/Resources/Bits.py
Twitch_Edog0049a/API/Resources/ChannelPoints.py
Twitch_Edog0049a/API/Resources/Channels.py
Twitch_Edog0049a/API/Resources/Charity.py
Twitch_Edog0049a/API/Resources/Chat.py
Twitch_Edog0049a/API/Resources/Clips.py
Twitch_Edog0049a/API/Resources/Entitlements.py
Twitch_Edog0049a/API/Resources/EventSub.py
Twitch_Edog0049a/API/Resources/Extensions.py
Twitch_Edog0049a/API/Resources/Games.py
Twitch_Edog0049a/API/Resources/Goals.py
Twitch_Edog0049a/API/Resources/HypeTrain.py
Twitch_Edog0049a/API/Resources/JWTGeneraotr.py
Twitch_Edog0049a/API/Resources/Moderation.py
Twitch_Edog0049a/API/Resources/Music.py
Twitch_Edog0049a/API/Resources/Polls.py
Twitch_Edog0049a/API/Resources/Predictions.py
Twitch_Edog0049a/API/Resources/Raids.py
Twitch_Edog0049a/API/Resources/ResponseTypes.py
Twitch_Edog0049a/API/Resources/Schedule.py
Twitch_Edog0049a/API/Resources/Search.py
Twitch_Edog0049a/API/Resources/Streams.py
Twitch_Edog0049a/API/Resources/Subscriptions.py
Twitch_Edog0049a/API/Resources/Teams.py
Twitch_Edog0049a/API/Resources/Users.py
Twitch_Edog0049a/API/Resources/Utils.py
Twitch_Edog0049a/API/Resources/Videos.py
Twitch_Edog0049a/API/Resources/Whispers.py
Twitch_Edog0049a/API/Resources/__TODO__.py
Twitch_Edog0049a/API/Resources/__imports.py
Twitch_Edog0049a/API/Resources/__init__.py
Twitch_Edog0049a/API/Resources/t.json
Twitch_Edog0049a/API/test/Ads_test.py
Twitch_Edog0049a/API/test/Bits_Test.py
Twitch_Edog0049a/API/test/Utils.py
Twitch_Edog0049a/API/test/__init__.py
Twitch_Edog0049a/ChatInterface/MessageHandler.py
Twitch_Edog0049a/ChatInterface/TwitchChatInterface.py
twitch_edog0049a-0.1.19.dist-info/METADATA
twitch_edog0049a-0.1.19.dist-info/WHEEL
twitch_edog0049a-0.1.19.dist-info/licenses/LICENSE.txt
twitch_edog0049a-0.1.19.dist-info/RECORD
