Metadata-Version: 2.3
Name: Twitch_Edog0049a
Version: 0.1.19
Summary: Twitch library for chat, api, pubs, and eventsub
Project-URL: Source code, https://github.com/eli-reid/twitch
Author-email: Eli Reid <Elir@elireid.com>
License-Expression: Apache-2.0 OR MIT
License-File: LICENSE.txt
Keywords: aiohttp,api,chat,chatbot,eventsub,irc,oauth,pubsub,requests,tmi,tmi.js,tmi.py,tmi.twitch.tv,twitch,twitch api,twitch api aiohttp,twitch api aiohttp3,twitch api aiohttp3.11,twitch api python,twitch api python3,twitch api python3.11,twitch api python3.11.0,twitch chat,twitch chat aiohttp,twitch chat aiohttp3,twitch chat aiohttp3.11,twitch chat python,twitch chat python3,twitch chat python3.11,twitch chat python3.11.0,twitch chatbot,twitch chatbot aiohttp,twitch chatbot aiohttp3,twitch ch
Requires-Python: >=3.10
Requires-Dist: aiohttp-cors>=0.7.0
Requires-Dist: aiohttp-jinja2>=1.4.2
Requires-Dist: aiohttp-oauth>=0.4.0
Requires-Dist: aiohttp-session>=2.9.0
Requires-Dist: aiohttp-socks>=0.6.0
Requires-Dist: aiohttp>=3.7.4.post0
Requires-Dist: asyncio>=3.4.3
Requires-Dist: eventhandler-edog0049a>=0.1.97
Requires-Dist: ircconnector-edog0049a>=0.1.0
Requires-Dist: requests>=2.26.0
Requires-Dist: websockets>=10.0
